hcam_widgets/__init__.py
hcam_widgets/astro.py
hcam_widgets/globals.py
hcam_widgets/hcam.py
hcam_widgets/logs.py
hcam_widgets/mimic.py
hcam_widgets/misc.py
hcam_widgets/tcs.py
hcam_widgets/tkutils.py
hcam_widgets/ucam.py
hcam_widgets/uspec.py
hcam_widgets/widgets.py
hcam_widgets/compo/__init__.py
hcam_widgets/compo/utils.py
hcam_widgets/compo/widgets.py
hcam_widgets/data/compo_lens_offset.csv
hcam_widgets/hardware/__init__.py
hcam_widgets/hardware/alarms.py
hcam_widgets/hardware/ccds.py
hcam_widgets/hardware/slide.py
hcam_widgets-1.2.2.dist-info/AUTHORS.rst
hcam_widgets-1.2.2.dist-info/LICENSE
hcam_widgets-1.2.2.dist-info/METADATA
hcam_widgets-1.2.2.dist-info/WHEEL
hcam_widgets-1.2.2.dist-info/top_level.txt
hcam_widgets-1.2.2.dist-info/RECORD
