Metadata-Version: 2.2
Name: hcam_widgets
Version: 1.2.2
Summary: Common Tkinter widgets for HiPerCAM
Home-page: https://github.com/HiPERCAM/hcam_widgets
Download-URL: https://github.com/HiPERCAM/hcam_widgets/archive/v1.2.2.tar.gz
Author: Stuart Littlefair
Author-email: s.littlefair@shef.ac.uk
License: MIT license
Keywords: hcam_widgets
Classifier: Development Status :: 2 - Pre-Alpha
Classifier: Intended Audience :: Developers
Classifier: License :: OSI Approved :: MIT License
Classifier: Natural Language :: English
Classifier: Programming Language :: Python :: 2
Classifier: Programming Language :: Python :: 2.6
Classifier: Programming Language :: Python :: 2.7
Classifier: Programming Language :: Python :: 3
Classifier: Programming Language :: Python :: 3.3
Classifier: Programming Language :: Python :: 3.4
Classifier: Programming Language :: Python :: 3.5
Requires-Python: >=3.6
License-File: LICENSE
License-File: AUTHORS.rst
Requires-Dist: astropy
Requires-Dist: requests
Requires-Dist: twisted
Requires-Dist: hcam_devices>=1.2.2
Requires-Dist: matplotlib
Requires-Dist: scipy
Requires-Dist: autobahn
Dynamic: author
Dynamic: author-email
Dynamic: classifier
Dynamic: description
Dynamic: download-url
Dynamic: home-page
Dynamic: keywords
Dynamic: license
Dynamic: requires-dist
Dynamic: requires-python
Dynamic: summary
